atomorm/__init__.py
atomorm/db.py
atomorm/fields.py
atomorm/model.py
atomorm-0.1.2.dist-info/licenses/LICENSE
atomorm-0.1.2.dist-info/METADATA
atomorm-0.1.2.dist-info/WHEEL
atomorm-0.1.2.dist-info/top_level.txt
atomorm-0.1.2.dist-info/RECORD
