Metadata-Version: 2.4
Name: atomorm
Version: 0.1.2
Summary: A lightweight ORM for SQLite in Python
Author-email: Chandra Dondeti <chandra.dondeti@outlook.com>
License: MIT
Project-URL: Homepage, https://github.com/csreddy98/atomorm
Project-URL: Source, https://github.com/csreddy98/atomorm
Requires-Python: >=3.9
License-File: LICENSE
Dynamic: license-file
